simplebert/__init__.py
simplebert/models.py
simplebert/pretrained.py
simplebert/pretrained_models.json
simplebert/tokenizers.py
simplebert/utils.py
simplebert-0.2.0.dist-info/LICENSE
simplebert-0.2.0.dist-info/METADATA
simplebert-0.2.0.dist-info/WHEEL
simplebert-0.2.0.dist-info/top_level.txt
simplebert-0.2.0.dist-info/RECORD
