Metadata-Version: 2.1
Name: simplebert
Version: 0.2.0
Summary: A package for transformer based NLP models.
Home-page: https://github.com/gaolichen/simplebert
Author: gaolichen
Author-email: galic.chen@gmail.com
License: UNKNOWN
Project-URL: Bug Tracker, https://github.com/gaolichen/simplebert/issues
Platform: UNKNOWN
Classifier: Programming Language :: Python :: 3
Classifier: License :: OSI Approved :: MIT License
Classifier: Operating System :: OS Independent
Requires-Python: >=3.6
License-File: LICENSE
Requires-Dist: numpy (>="1.19.5")
Requires-Dist: tensorflow (>="2.5.0")
